[
  {
    "id": "m-1",
    "name": "Feed Ads - Product Focus",
    "platform": "meta",
    "startDate": "2025-04-21",
    "endDate": null,
    "budget": 7500,
    "spend": 4500,
    "status": "active",
    "impressions": 400000,
    "reach": 180000,
    "frequency": 2.22,
    "clicks": 12000,
    "ctr": 3,
    "cpm": 11.25,
    "cpc": 0.38,
    "conversions": 480,
    "costPerResult": 9.38,
    "engagement": 24000,
    "relevanceScore": 8
  },
  {
    "id": "m-2",
    "name": "Instagram Stories",
    "platform": "meta",
    "startDate": "2025-04-06",
    "endDate": null,
    "budget": 5000,
    "spend": 3750,
    "status": "active",
    "impressions": 350000,
    "reach": 150000,
    "frequency": 2.33,
    "clicks": 8750,
    "ctr": 2.5,
    "cpm": 10.71,
    "cpc": 0.43,
    "conversions": 350,
    "costPerResult": 10.71,
    "engagement": 21000,
    "relevanceScore": 7
  },
  {
    "id": "m-3",
    "name": "Lookalike Audience",
    "platform": "meta",
    "startDate": "2025-05-06",
    "endDate": null,
    "budget": 4000,
    "spend": 1200,
    "status": "active",
    "impressions": 120000,
    "reach": 60000,
    "frequency": 2,
    "clicks": 3600,
    "ctr": 3,
    "cpm": 10,
    "cpc": 0.33,
    "conversions": 144,
    "costPerResult": 8.33,
    "engagement": 7200,
    "relevanceScore": 9
  },
  {
    "id": "m-4",
    "name": "Retargeting Campaign",
    "platform": "meta",
    "startDate": "2025-02-20",
    "endDate": "2025-04-21",
    "budget": 6000,
    "spend": 6000,
    "status": "completed",
    "impressions": 280000,
    "reach": 100000,
    "frequency": 2.8,
    "clicks": 11200,
    "ctr": 4,
    "cpm": 21.43,
    "cpc": 0.54,
    "conversions": 560,
    "costPerResult": 10.71,
    "engagement": 22400,
    "relevanceScore": 9
  }
]
